[{"model": "creator.OccupationSkills", "fields": {"occupation": 56, "skill": 197, "optional": false, "category": "1", "limit": 0}},
{"model": "creator.OccupationSkills", "fields": {"occupation": 56, "skill": 223, "optional": false, "category": "1", "limit": 0}},
{"model": "creator.OccupationSkills", "fields": {"occupation": 56, "skill": 234, "optional": false, "category": "1", "limit": 0}},
{"model": "creator.OccupationSkills", "fields": {"occupation": 56, "skill": 237, "optional": false, "category": "1", "limit": 0}},
{"model": "creator.OccupationSkills", "fields": {"occupation": 56, "skill": 245, "optional": false, "category": "1", "limit": 0}},
{"model": "creator.OccupationSkills", "fields": {"occupation": 56, "skill": 251, "optional": false, "category": "1", "limit": 0}},
{"model": "creator.OccupationSkills", "fields": {"occupation": 56, "skill": 252, "optional": false, "category": "1", "limit": 0}},
{"model": "creator.OccupationSkills", "fields": {"occupation": 56, "skill": 264, "optional": false, "category": "1", "limit": 0}}]